{
  "$id": "endocrinologyDiabetesAndMetabolism",
  "$schema": "https://schema.yext.com/config/km/entity-template/v2",
  "content": {
    "taxonomy_relatedConditions": [
      "CON-2356",
      "CON-2361",
      "CON-2363",
      "CON-2365",
      "CON-2371",
      "CON-2372",
      "CON-2373",
      "CON-2377",
      "CON-2380",
      "CON-2381",
      "CON-2384",
      "CON-2385",
      "CON-2387",
      "CON-2389",
      "CON-2390",
      "CON-2392",
      "CON-2393",
      "CON-2394",
      "CON-2395",
      "CON-2398",
      "CON-2404",
      "CON-2405",
      "CON-2407",
      "CON-2410",
      "CON-244",
      "CON-1560",
      "CON-2412",
      "CON-2413",
      "CON-2415",
      "CON-2417",
      "CON-2418",
      "CON-2419",
      "CON-2420",
      "CON-2422",
      "CON-2423",
      "CON-2424",
      "CON-2425",
      "CON-2428",
      "CON-2402",
      "CON-2430",
      "CON-2431",
      "CON-2433",
      "CON-2434",
      "CON-2435",
      "CON-2436",
      "CON-2437",
      "CON-2440",
      "CON-2441",
      "CON-2443",
      "CON-2444",
      "CON-2445",
      "CON-2450",
      "CON-2451",
      "CON-2453",
      "CON-2462",
      "CON-2463",
      "CON-2464",
      "CON-2465",
      "CON-2469",
      "CON-2470",
      "CON-2471",
      "CON-2473",
      "CON-2474",
      "CON-2475",
      "CON-2477",
      "CON-2478",
      "CON-2481",
      "CON-2485",
      "CON-2486",
      "CON-2487",
      "CON-2488",
      "CON-2489",
      "CON-2490",
      "CON-2491",
      "CON-2492",
      "CON-2494",
      "CON-2496",
      "CON-2497",
      "CON-2499",
      "CON-2501",
      "CON-2503",
      "CON-2508",
      "CON-2510",
      "CON-2511",
      "CON-2512",
      "CON-2514",
      "CON-2517",
      "CON-2519",
      "CON-1138",
      "CON-2520",
      "CON-2521",
      "CON-2522",
      "CON-2525",
      "CON-2534",
      "CON-2536",
      "CON-2538",
      "CON-2539",
      "CON-2542",
      "CON-2547",
      "CON-2548",
      "CON-2550",
      "CON-2551",
      "CON-2552",
      "CON-2558",
      "CON-2560",
      "CON-2564",
      "CON-2568",
      "CON-2569",
      "CON-2570",
      "CON-2571",
      "CON-2572",
      "CON-2573",
      "CON-2574",
      "CON-2575",
      "CON-2577",
      "CON-2581",
      "CON-2582",
      "CON-2584",
      "CON-2586",
      "CON-2587",
      "CON-2588",
      "CON-2591",
      "CON-241",
      "CON-2154",
      "CON-2188",
      "CON-4844",
      "CON-4758",
      "CON-4845",
      "CON-2421",
      "CON-237",
      "CON-245",
      "CON-7172",
      "CON-318",
      "CON-2115",
      "CON-5220",
      "CON-5221",
      "CON-7173",
      "CON-234",
      "CON-5224",
      "CON-319",
      "CON-235",
      "CON-316",
      "CON-2148",
      "CON-2150",
      "CON-1798",
      "CON-924",
      "CON-2592"
    ],
    "taxonomy_relatedProcedures": [
      "PROC-13223",
      "PROC-13224",
      "PROC-13226",
      "PROC-13230",
      "PROC-2416",
      "PROC-13235",
      "PROC-13236",
      "PROC-13152",
      "PROC-13239",
      "PROC-13240",
      "PROC-13241",
      "PROC-14598",
      "PROC-13243",
      "PROC-15222",
      "PROC-13244",
      "PROC-13246",
      "PROC-13249",
      "PROC-13250",
      "PROC-13254",
      "PROC-13255"
    ],
    "taxonomy_relatedReasonsForVisit": [
      "REAS-15611",
      "REAS-15671",
      "REAS-15673",
      "REAS-15674",
      "REAS-15679",
      "REAS-15680",
      "REAS-15942"
    ],
    "taxonomy_relatedSpecialties": [
      "SPEC-12"
    ]
  },
  "entityTypes": [
    "healthcareProfessional"
  ],
  "name": "Endocrinology, Diabetes and Metabolism"
}