{
  "$id": "otolaryngology",
  "$schema": "https://schema.yext.com/config/km/entity-template/v2",
  "content": {
    "taxonomy_relatedConditions": [
      "CON-370",
      "CON-2246",
      "CON-5278",
      "CON-5283",
      "CON-5285",
      "CON-5287",
      "CON-5289",
      "CON-5291",
      "CON-5293",
      "CON-5294",
      "CON-5295",
      "CON-5296",
      "CON-5297",
      "CON-6563",
      "CON-6568",
      "CON-6569",
      "CON-6570",
      "CON-6572",
      "CON-6573",
      "CON-6574",
      "CON-6576",
      "CON-6578",
      "CON-6579",
      "CON-6581",
      "CON-6583",
      "CON-6584",
      "CON-6586",
      "CON-6588",
      "CON-6589",
      "CON-6590",
      "CON-6592",
      "CON-6598",
      "CON-6599",
      "CON-6601",
      "CON-6603",
      "CON-6605",
      "CON-6606",
      "CON-6607",
      "CON-6610",
      "CON-6611",
      "CON-6613",
      "CON-6614",
      "CON-6615",
      "CON-6616",
      "CON-6617",
      "CON-6619",
      "CON-6620",
      "CON-6621",
      "CON-6622",
      "CON-6629",
      "CON-6630",
      "CON-6632",
      "CON-6642",
      "CON-6643",
      "CON-6644",
      "CON-6648",
      "CON-6652",
      "CON-6655",
      "CON-6657",
      "CON-6658",
      "CON-6659",
      "CON-6663",
      "CON-6664",
      "CON-6665",
      "CON-6670",
      "CON-6676",
      "CON-6677",
      "CON-6680",
      "CON-6681",
      "CON-6682",
      "CON-6683",
      "CON-6687",
      "CON-6688",
      "CON-6689",
      "CON-6690",
      "CON-6694",
      "CON-6696",
      "CON-6697",
      "CON-6698",
      "CON-6699",
      "CON-6700",
      "CON-6702",
      "CON-6705",
      "CON-6706",
      "CON-6707",
      "CON-6716",
      "CON-6718",
      "CON-6720",
      "CON-6721",
      "CON-6729",
      "CON-6730",
      "CON-4727",
      "CON-231",
      "CON-12230",
      "CON-12232",
      "CON-12234",
      "CON-3762",
      "CON-524"
    ],
    "taxonomy_relatedProcedures": [
      "PROC-13015",
      "PROC-13016",
      "PROC-13018",
      "PROC-13030",
      "PROC-13051",
      "PROC-13090",
      "PROC-13169",
      "PROC-13175",
      "PROC-13176",
      "PROC-13177",
      "PROC-13179",
      "PROC-13182",
      "PROC-13183",
      "PROC-13184",
      "PROC-13185",
      "PROC-13187",
      "PROC-13188",
      "PROC-13189",
      "PROC-13190",
      "PROC-13191",
      "PROC-13192",
      "PROC-13193",
      "PROC-13194",
      "PROC-13195",
      "PROC-13196",
      "PROC-13197",
      "PROC-13199",
      "PROC-13200",
      "PROC-13202",
      "PROC-13203",
      "PROC-13205",
      "PROC-13206",
      "PROC-13207",
      "PROC-13209",
      "PROC-13210",
      "PROC-13211",
      "PROC-13213",
      "PROC-13214",
      "PROC-13215",
      "PROC-13232",
      "PROC-13248",
      "PROC-13275",
      "PROC-13299",
      "PROC-13304",
      "PROC-13308",
      "PROC-13309",
      "PROC-13321",
      "PROC-13327",
      "PROC-13335",
      "PROC-13341",
      "PROC-13347",
      "PROC-13353",
      "PROC-13354",
      "PROC-13356",
      "PROC-13380",
      "PROC-13431",
      "PROC-13466",
      "PROC-13467",
      "PROC-13472",
      "PROC-13473",
      "PROC-13956",
      "PROC-13958",
      "PROC-13960",
      "PROC-13961",
      "PROC-13962",
      "PROC-13963",
      "PROC-13966",
      "PROC-13967",
      "PROC-13968",
      "PROC-13969",
      "PROC-14438",
      "PROC-15222"
    ],
    "taxonomy_relatedReasonsForVisit": [
      "REAS-15664",
      "REAS-15665",
      "REAS-15666",
      "REAS-15669",
      "REAS-15715",
      "REAS-15716",
      "REAS-15730",
      "REAS-15731",
      "REAS-15736",
      "REAS-15811"
    ],
    "taxonomy_relatedSpecialties": [
      "SPEC-29"
    ]
  },
  "entityTypes": [
    "healthcareProfessional"
  ],
  "name": "Otolaryngology"
}